[
  {
    "name": "Eirika",
    "portraitPath": "portraits/FE8/eirika.png",
    "paletteString": "344FDF6F3F477D2ED3252C2587206377A26245416261FE335B23BA105373FE7F",
    "description1": "The princess of the kingdom of",
    "description2": "Renais. She's elegant and kind.",
    "characterClass": "EIRIKA_LORD",
    "level": 1,
    "bases": {
      "hp": 0,
      "str": 0,
      "skl": 0,
      "spd": 0,
      "def": 0,
      "res": 0,
      "lck": 5
    },
    "growths": {
      "hp": 70,
      "str": 40,
      "skl": 60,
      "spd": 60,
      "def": 30,
      "res": 30,
      "lck": 60
    },
    "weaponRanks": [
      1,
      0,
      0,
      0,
      0,
      0,
      0,
      0
    ],
    "constitution": 0,
    "originGame": "FE8",
    "eyeX": 3,
    "eyeY": 4,
    "mouthX": 2,
    "mouthY": 6
  },
  {
    "name": "Seth",
    "portraitPath": "portraits/FE8/seth.png",
    "paletteString": "344FFF635F3B7D2AD3252C258720570410004C0CEF662B468731FF275373FE7F",
    "description1": "A young commander of Renais.",
    "description2": "He's calm, composed, and skilled.",
    "characterClass": "PALADIN",
    "level": 1,
    "bases": {
      "hp": 7,
      "str": 7,
      "skl": 9,
      "spd": 5,
      "def": 3,
      "res": 5,
      "lck": 13
    },
    "growths": {
      "hp": 90,
      "str": 50,
      "skl": 45,
      "spd": 45,
      "def": 40,
      "res": 30,
      "lck": 25
    },
    "weaponRanks": [
      181,
      181,
      0,
      0,
      0,
      0,
      0,
      0
    ],
    "constitution": 0,
    "originGame": "FE8",
    "eyeX": 3,
    "eyeY": 3,
    "mouthX": 2,
    "mouthY": 5
  },
  {
    "name": "Gilliam",
    "portraitPath": "portraits/FE8/gilliam.png",
    "paletteString": "344FFF635F3B7D2AD3252C25872010368C250921264AE12D412DFF275373FE7F",
    "description1": "An armored knight of Frelia.",
    "description2": "He's quiet yet dependable.",
    "characterClass": "KNIGHT",
    "level": 4,
    "bases": {
      "hp": 8,
      "str": 4,
      "skl": 4,
      "spd": 3,
      "def": 0,
      "res": 3,
      "lck": 3
    },
    "growths": {
      "hp": 90,
      "str": 45,
      "skl": 35,
      "spd": 30,
      "def": 55,
      "res": 20,
      "lck": 30
    },
    "weaponRanks": [
      0,
      71,
      0,
      0,
      0,
      0,
      0,
      0
    ],
    "constitution": 1,
    "originGame": "FE8",
    "eyeX": 3,
    "eyeY": 3,
    "mouthX": 2,
    "mouthY": 5
  },
  {
    "name": "Franz",
    "portraitPath": "portraits/FE8/franz.png",
    "paletteString": "344FFF635F3B7D2AD3252C2587205D1B9812B01D972BF30EEB09D14E0B36FE7F",
    "description1": "An earnest and compassionate",
    "description2": "cavalier from Renais.",
    "characterClass": "CAVALIER",
    "level": 1,
    "bases": {
      "hp": 0,
      "str": 2,
      "skl": 3,
      "spd": 2,
      "def": 0,
      "res": 1,
      "lck": 2
    },
    "growths": {
      "hp": 80,
      "str": 40,
      "skl": 40,
      "spd": 50,
      "def": 25,
      "res": 20,
      "lck": 40
    },
    "weaponRanks": [
      1,
      31,
      0,
      0,
      0,
      0,
      0,
      0
    ],
    "constitution": 0,
    "originGame": "FE8",
    "eyeX": 3,
    "eyeY": 4,
    "mouthX": 2,
    "mouthY": 6
  },
  {
    "name": "Moulder",
    "portraitPath": "portraits/FE8/moulder.png",
    "paletteString": "344FFF635F3B7D2AD3252C258720361A900D0C11DE5F1853EF2D7815B0048B04",
    "description1": "A mature priest of Frelia. He's",
    "description2": "gentle and reassuring.",
    "characterClass": "PRIEST",
    "level": 3,
    "bases": {
      "hp": 2,
      "str": 3,
      "skl": 5,
      "spd": 7,
      "def": 1,
      "res": 0,
      "lck": 1
    },
    "growths": {
      "hp": 70,
      "str": 40,
      "skl": 50,
      "spd": 40,
      "def": 25,
      "res": 25,
      "lck": 20
    },
    "weaponRanks": [
      0,
      0,
      0,
      0,
      71,
      0,
      0,
      0
    ],
    "constitution": 4,
    "originGame": "FE8",
    "eyeX": 3,
    "eyeY": 3,
    "mouthX": 2,
    "mouthY": 5
  },
  {
    "name": "Vanessa",
    "portraitPath": "portraits/FE8/vanessa.png",
    "paletteString": "344FFF635F3B7D2AD3252C258720671FA51A871D9F193721776F6D52FF27FE7F",
    "description1": "A sincere, honest, and honorable",
    "description2": "pegasus knight of Frelia.",
    "characterClass": "PEGASUS_KNIGHT",
    "level": 1,
    "bases": {
      "hp": 3,
      "str": 1,
      "skl": 2,
      "spd": 6,
      "def": 3,
      "res": 3,
      "lck": 4
    },
    "growths": {
      "hp": 50,
      "str": 35,
      "skl": 55,
      "spd": 60,
      "def": 20,
      "res": 30,
      "lck": 50
    },
    "weaponRanks": [
      0,
      31,
      0,
      0,
      0,
      0,
      0,
      0
    ],
    "constitution": 0,
    "originGame": "FE8",
    "eyeX": 3,
    "eyeY": 4,
    "mouthX": 2,
    "mouthY": 6
  },
  {
    "name": "Ross",
    "portraitPath": "portraits/FE8/ross.png",
    "paletteString": "344FFF635F3B7D2AD3252C258720CE414A29EA2498193019626103453667FE7F",
    "description1": "A young villager. He longs to be a",
    "description2": "warrior, like his father.",
    "characterClass": "TRAINEE",
    "level": 1,
    "bases": {
      "hp": 1,
      "str": 2,
      "skl": 2,
      "spd": 2,
      "def": 2,
      "res": 0,
      "lck": 8
    },
    "growths": {
      "hp": 70,
      "str": 50,
      "skl": 35,
      "spd": 30,
      "def": 25,
      "res": 20,
      "lck": 40
    },
    "weaponRanks": [
      0,
      0,
      1,
      0,
      0,
      0,
      0,
      0
    ],
    "constitution": 0,
    "originGame": "FE8",
    "eyeX": 3,
    "eyeY": 4,
    "mouthX": 3,
    "mouthY": 6
  },
  {
    "name": "Neimi",
    "portraitPath": "portraits/FE8/neimi.png",
    "paletteString": "344FDF6F3F477D2ED3252C2587201D4D793CB1286A14D523D00EEB09FF27FE7F",
    "description1": "A childhood friend of Colm who",
    "description2": "hails from Renais. She cries a lot.",
    "characterClass": "ARCHER_F",
    "level": 1,
    "bases": {
      "hp": 0,
      "str": 1,
      "skl": 2,
      "spd": 2,
      "def": 0,
      "res": 2,
      "lck": 4
    },
    "growths": {
      "hp": 55,
      "str": 45,
      "skl": 50,
      "spd": 60,
      "def": 15,
      "res": 35,
      "lck": 50
    },
    "weaponRanks": [
      0,
      0,
      0,
      31,
      0,
      0,
      0,
      0
    ],
    "constitution": 0,
    "originGame": "FE8",
    "eyeX": 3,
    "eyeY": 4,
    "mouthX": 2,
    "mouthY": 6
  },
  {
    "name": "Colm",
    "portraitPath": "portraits/FE8/colm.png",
    "paletteString": "344FFF635F3B7D2AD3252C258720E2616149022D9819684DE72C714E5767FE7F",
    "description1": "A childhood friend of Neimi who",
    "description2": "hails from Renais. He can be snide.",
    "characterClass": "THIEF",
    "level": 2,
    "bases": {
      "hp": 2,
      "str": 1,
      "skl": 3,
      "spd": 1,
      "def": 1,
      "res": 1,
      "lck": 8
    },
    "growths": {
      "hp": 75,
      "str": 40,
      "skl": 40,
      "spd": 65,
      "def": 25,
      "res": 20,
      "lck": 45
    },
    "weaponRanks": [
      1,
      0,
      0,
      0,
      0,
      0,
      0,
      0
    ],
    "constitution": 0,
    "originGame": "FE8",
    "eyeX": 3,
    "eyeY": 3,
    "mouthX": 3,
    "mouthY": 5
  },
  {
    "name": "Garcia",
    "portraitPath": "portraits/FE8/garcia.png",
    "paletteString": "344FFF635F3B7D2AD3252C258720CE414A29EA249819301962614F4A5767FE7F",
    "description1": "A villager from Renais. He was",
    "description2": "once a feared military leader.",
    "characterClass": "FIGHTER",
    "level": 4,
    "bases": {
      "hp": 8,
      "str": 3,
      "skl": 5,
      "spd": 3,
      "def": 3,
      "res": 1,
      "lck": 3
    },
    "growths": {
      "hp": 80,
      "str": 65,
      "skl": 40,
      "spd": 20,
      "def": 25,
      "res": 15,
      "lck": 40
    },
    "weaponRanks": [
      0,
      0,
      71,
      0,
      0,
      0,
      0,
      0
    ],
    "constitution": 3,
    "originGame": "FE8",
    "eyeX": 3,
    "eyeY": 3,
    "mouthX": 2,
    "mouthY": 5
  },
  {
    "name": "Innes",
    "portraitPath": "portraits/FE8/innes.png",
    "paletteString": "344FFF635F3B7D2AD3252C258720174B703A6A25746FAC56C8418F55E93CFE7F",
    "description1": "The prince of Frelia. He's brash",
    "description2": "and arrogant, but good at heart.",
    "characterClass": "SNIPER",
    "level": 1,
    "bases": {
      "hp": 10,
      "str": 7,
      "skl": 7,
      "spd": 10,
      "def": 5,
      "res": 7,
      "lck": 14
    },
    "growths": {
      "hp": 75,
      "str": 40,
      "skl": 40,
      "spd": 45,
      "def": 20,
      "res": 25,
      "lck": 45
    },
    "weaponRanks": [
      0,
      0,
      0,
      181,
      0,
      0,
      0,
      0
    ],
    "constitution": 1,
    "originGame": "FE8",
    "eyeX": 3,
    "eyeY": 3,
    "mouthX": 2,
    "mouthY": 5
  },
  {
    "name": "Lute",
    "portraitPath": "portraits/FE8/lute.png",
    "paletteString": "344FDF6F3F477D2ED3252C258720B66C7254AC345373825E2541FF271813FE7F",
    "description1": "A young mage of Renais. She",
    "description2": "believes she is a prodigy.",
    "characterClass": "MAGE_F",
    "level": 1,
    "bases": {
      "hp": 1,
      "str": 5,
      "skl": 3,
      "spd": 5,
      "def": 1,
      "res": 1,
      "lck": 8
    },
    "growths": {
      "hp": 45,
      "str": 65,
      "skl": 30,
      "spd": 45,
      "def": 15,
      "res": 40,
      "lck": 45
    },
    "weaponRanks": [
      0,
      0,
      0,
      0,
      0,
      71,
      0,
      0
    ],
    "constitution": 0,
    "originGame": "FE8",
    "eyeX": 3,
    "eyeY": 4,
    "mouthX": 2,
    "mouthY": 6
  },
  {
    "name": "Natasha",
    "portraitPath": "portraits/FE8/natasha.png",
    "paletteString": "344FDF6F3F477D2ED3252C258720FF335A2394168D19C37542616A395767FE7F",
    "description1": "A beautiful cleric from the Grado",
    "description2": "Empire. She's graceful and serious.",
    "characterClass": "CLERIC",
    "level": 1,
    "bases": {
      "hp": 2,
      "str": 1,
      "skl": 2,
      "spd": 6,
      "def": 2,
      "res": 0,
      "lck": 6
    },
    "growths": {
      "hp": 50,
      "str": 60,
      "skl": 25,
      "spd": 40,
      "def": 15,
      "res": 55,
      "lck": 60
    },
    "weaponRanks": [
      0,
      0,
      0,
      0,
      31,
      0,
      0,
      0
    ],
    "constitution": 0,
    "originGame": "FE8",
    "eyeX": 3,
    "eyeY": 4,
    "mouthX": 2,
    "mouthY": 6
  },
  {
    "name": "Cormag",
    "portraitPath": "portraits/FE8/cormag.png",
    "paletteString": "344F5F477D2EF725911D2C258720FF5F7B33B51ACE192A4E86390525766FFE7F",
    "description1": "A wyvern knight of Grado. A gentle",
    "description2": "man, but a ferocious warrior.",
    "characterClass": "WYVERN_RIDER",
    "level": 9,
    "bases": {
      "hp": 10,
      "str": 7,
      "skl": 6,
      "spd": 5,
      "def": 4,
      "res": 2,
      "lck": 4
    },
    "growths": {
      "hp": 85,
      "str": 55,
      "skl": 40,
      "spd": 45,
      "def": 25,
      "res": 15,
      "lck": 35
    },
    "weaponRanks": [
      0,
      71,
      0,
      0,
      0,
      0,
      0,
      0
    ],
    "constitution": 1,
    "originGame": "FE8",
    "eyeX": 3,
    "eyeY": 3,
    "mouthX": 2,
    "mouthY": 5
  },
  {
    "name": "Ephraim",
    "portraitPath": "portraits/FE8/ephraim.png",
    "paletteString": "344FFF635F3B7D2AD3252C258720225B6252683983652241F47A2D662831FE7F",
    "description1": "The prince of Renais. He is a man",
    "description2": "of great honor and bravery.",
    "characterClass": "EPHRAIM_LORD",
    "level": 4,
    "bases": {
      "hp": 5,
      "str": 2,
      "skl": 3,
      "spd": 4,
      "def": 1,
      "res": 2,
      "lck": 8
    },
    "growths": {
      "hp": 80,
      "str": 55,
      "skl": 55,
      "spd": 45,
      "def": 35,
      "res": 25,
      "lck": 50
    },
    "weaponRanks": [
      0,
      31,
      0,
      0,
      0,
      0,
      0,
      0
    ],
    "constitution": 0,
    "originGame": "FE8",
    "eyeX": 3,
    "eyeY": 3,
    "mouthX": 2,
    "mouthY": 5
  },
  {
    "name": "Forde",
    "portraitPath": "portraits/FE8/forde.png",
    "paletteString": "344FFF635F3B7D2AD3252C2587207D07D906F3151815B308AD08312FE80DFE7F",
    "description1": "A cavalier of Renais. He is skilled,",
    "description2": "but reckless. He's Franz's brother.",
    "characterClass": "CAVALIER",
    "level": 5,
    "bases": {
      "hp": 4,
      "str": 2,
      "skl": 6,
      "spd": 3,
      "def": 2,
      "res": 2,
      "lck": 7
    },
    "growths": {
      "hp": 85,
      "str": 40,
      "skl": 50,
      "spd": 45,
      "def": 20,
      "res": 25,
      "lck": 35
    },
    "weaponRanks": [
      31,
      71,
      0,
      0,
      0,
      0,
      0,
      0
    ],
    "constitution": 0,
    "originGame": "FE8",
    "eyeX": 3,
    "eyeY": 3,
    "mouthX": 2,
    "mouthY": 5
  },
  {
    "name": "Kyle",
    "portraitPath": "portraits/FE8/kyle.png",
    "paletteString": "344FFF635F3B7D2AD3252C258720C3120106630D7232CB2548216725BF27FE7F",
    "description1": "A steadfast and honorable cavalier",
    "description2": "in sworn service to Renais.",
    "characterClass": "CAVALIER",
    "level": 6,
    "bases": {
      "hp": 5,
      "str": 4,
      "skl": 4,
      "spd": 2,
      "def": 3,
      "res": 1,
      "lck": 6
    },
    "growths": {
      "hp": 90,
      "str": 50,
      "skl": 40,
      "spd": 40,
      "def": 25,
      "res": 20,
      "lck": 20
    },
    "weaponRanks": [
      31,
      71,
      0,
      0,
      0,
      0,
      0,
      0
    ],
    "constitution": 1,
    "originGame": "FE8",
    "eyeX": 3,
    "eyeY": 3,
    "mouthX": 2,
    "mouthY": 5
  },
  {
    "name": "Amelia",
    "portraitPath": "portraits/FE8/amelia.png",
    "paletteString": "344FFF635F3B7D2AD3252C258720DE1F1817101EFF353D0DD70C4736346BFE7F",
    "description1": "A young girl from a small village in",
    "description2": "Grado. She is honest and sincere.",
    "characterClass": "RECRUIT",
    "level": 1,
    "bases": {
      "hp": 3,
      "str": 1,
      "skl": 3,
      "spd": 3,
      "def": 2,
      "res": 2,
      "lck": 6
    },
    "growths": {
      "hp": 60,
      "str": 35,
      "skl": 40,
      "spd": 40,
      "def": 30,
      "res": 15,
      "lck": 50
    },
    "weaponRanks": [
      0,
      1,
      0,
      0,
      0,
      0,
      0,
      0
    ],
    "constitution": 0,
    "originGame": "FE8",
    "eyeX": 3,
    "eyeY": 4,
    "mouthX": 2,
    "mouthY": 6
  },
  {
    "name": "Artur",
    "portraitPath": "portraits/FE8/artur.png",
    "paletteString": "344FFF635F3B7D2AD3252C2587201F127911F108EE7F0C63C739714E5767FE7F",
    "description1": "A young monk from Renais. He is a",
    "description2": "very forthright and pious man.",
    "characterClass": "MONK",
    "level": 2,
    "bases": {
      "hp": 1,
      "str": 5,
      "skl": 5,
      "spd": 6,
      "def": 1,
      "res": 1,
      "lck": 2
    },
    "growths": {
      "hp": 55,
      "str": 50,
      "skl": 50,
      "spd": 40,
      "def": 15,
      "res": 55,
      "lck": 25
    },
    "weaponRanks": [
      0,
      0,
      0,
      0,
      0,
      0,
      1,
      0
    ],
    "constitution": 0,
    "originGame": "FE8",
    "eyeX": 3,
    "eyeY": 3,
    "mouthX": 2,
    "mouthY": 5
  },
  {
    "name": "Gerik",
    "portraitPath": "portraits/FE8/gerik.png",
    "paletteString": "344FFF635F3B7D2AD3252C258720F30E2D0E6A05FE33D334AC20782A1463FE7F",
    "description1": "A mercenary leader from Jehanna. He's",
    "description2": "better known as the Desert Tiger.",
    "characterClass": "MERCENARY",
    "level": 10,
    "bases": {
      "hp": 14,
      "str": 10,
      "skl": 5,
      "spd": 5,
      "def": 6,
      "res": 4,
      "lck": 8
    },
    "growths": {
      "hp": 90,
      "str": 45,
      "skl": 40,
      "spd": 30,
      "def": 35,
      "res": 25,
      "lck": 30
    },
    "weaponRanks": [
      71,
      0,
      0,
      0,
      0,
      0,
      0,
      0
    ],
    "constitution": 4,
    "originGame": "FE8",
    "eyeX": 3,
    "eyeY": 2,
    "mouthX": 2,
    "mouthY": 4
  },
  {
    "name": "Tethys",
    "portraitPath": "portraits/FE8/tethys.png",
    "paletteString": "344FDF6F3F477D2ED3252C258720FD14790C9008FF52FF31FF27AC20734E3567",
    "description1": "A beautiful and charming dancer",
    "description2": "from Jehanna.",
    "characterClass": "DANCER",
    "level": 1,
    "bases": {
      "hp": 4,
      "str": 0,
      "skl": 0,
      "spd": 5,
      "def": 5,
      "res": 3,
      "lck": 10
    },
    "growths": {
      "hp": 85,
      "str": 5,
      "skl": 10,
      "spd": 70,
      "def": 30,
      "res": 75,
      "lck": 80
    },
    "weaponRanks": [
      0,
      0,
      0,
      0,
      0,
      0,
      0,
      0
    ],
    "constitution": 1,
    "originGame": "FE8",
    "eyeX": 3,
    "eyeY": 4,
    "mouthX": 2,
    "mouthY": 6
  },
  {
    "name": "Marisa",
    "portraitPath": "portraits/FE8/marisa.png",
    "paletteString": "344FDF6F3F477D2ED3252C2587201F7E5A6D30457C0456040421FF275573FE7F",
    "description1": "An aloof sword fighter from Jehanna.",
    "description2": "She's known as the Crimson Flash.",
    "characterClass": "MYRMIDON_F",
    "level": 5,
    "bases": {
      "hp": 8,
      "str": 4,
      "skl": 3,
      "spd": 3,
      "def": 3,
      "res": 2,
      "lck": 9
    },
    "growths": {
      "hp": 75,
      "str": 30,
      "skl": 55,
      "spd": 60,
      "def": 15,
      "res": 25,
      "lck": 50
    },
    "weaponRanks": [
      31,
      0,
      0,
      0,
      0,
      0,
      0,
      0
    ],
    "constitution": 0,
    "originGame": "FE8",
    "eyeX": 3,
    "eyeY": 4,
    "mouthX": 2,
    "mouthY": 6
  },
  {
    "name": "Saleh",
    "portraitPath": "portraits/FE8/saleh.png",
    "paletteString": "344FFF635F3B7D2AD3252C258720554EB0352B2D984BB14AAA31591E5373FE7F",
    "description1": "A sage from the village Caer Pelyn.",
    "description2": "He's Ewan's solemn, but kind, teacher.",
    "characterClass": "SAGE",
    "level": 2,
    "bases": {
      "hp": 10,
      "str": 11,
      "skl": 14,
      "spd": 10,
      "def": 3,
      "res": 8,
      "lck": 11
    },
    "growths": {
      "hp": 50,
      "str": 30,
      "skl": 25,
      "spd": 40,
      "def": 30,
      "res": 35,
      "lck": 40
    },
    "weaponRanks": [
      0,
      0,
      0,
      0,
      71,
      181,
      121,
      0
    ],
    "constitution": 1,
    "originGame": "FE8",
    "eyeX": 3,
    "eyeY": 3,
    "mouthX": 2,
    "mouthY": 5
  },
  {
    "name": "Ewan",
    "portraitPath": "portraits/FE8/ewan.png",
    "paletteString": "344FFF635F3B7D2AD3252C2587203D15B90CB008087A6261357B4E6E8B3DFE7F",
    "description1": "A sage-in-training from Jehanna.",
    "description2": "He reveres his teacher, Saleh.",
    "characterClass": "PUPIL",
    "level": 2,
    "bases": {
      "hp": 2,
      "str": 2,
      "skl": 2,
      "spd": 4,
      "def": 0,
      "res": 0,
      "lck": 5
    },
    "growths": {
      "hp": 50,
      "str": 45,
      "skl": 40,
      "spd": 35,
      "def": 15,
      "res": 40,
      "lck": 50
    },
    "weaponRanks": [
      0,
      0,
      0,
      0,
      0,
      1,
      0,
      0
    ],
    "constitution": 0,
    "originGame": "FE8",
    "eyeX": 3,
    "eyeY": 5,
    "mouthX": 3,
    "mouthY": 7
  },
  {
    "name": "L'Arachel",
    "portraitPath": "portraits/FE8/l'arachel.png",
    "paletteString": "344FDF6F3F477D2ED3252C258720D61710072D0E6A154948ED5DFF275573FE7F",
    "description1": "A young woman from Rausten. She",
    "description2": "fights for justice and order.",
    "characterClass": "TROUBADOUR",
    "level": 3,
    "bases": {
      "hp": 3,
      "str": 5,
      "skl": 5,
      "spd": 7,
      "def": 3,
      "res": 3,
      "lck": 12
    },
    "growths": {
      "hp": 45,
      "str": 50,
      "skl": 45,
      "spd": 45,
      "def": 15,
      "res": 50,
      "lck": 65
    },
    "weaponRanks": [
      0,
      0,
      0,
      0,
      31,
      0,
      0,
      0
    ],
    "constitution": 0,
    "originGame": "FE8",
    "eyeX": 3,
    "eyeY": 4,
    "mouthX": 2,
    "mouthY": 6
  },
  {
    "name": "Dozla",
    "portraitPath": "portraits/FE8/dozla.png",
    "paletteString": "344FFF635F3B7D2AD3252C2587204B2686150715BE21B808F110FF275373FE7F",
    "description1": "A berserker from Rausten. He's a",
    "description2": "hearty man with a thirst for life.",
    "characterClass": "BERSERKER",
    "level": 1,
    "bases": {
      "hp": 19,
      "str": 9,
      "skl": 5,
      "spd": 2,
      "def": 5,
      "res": 6,
      "lck": 4
    },
    "growths": {
      "hp": 85,
      "str": 50,
      "skl": 35,
      "spd": 40,
      "def": 30,
      "res": 25,
      "lck": 30
    },
    "weaponRanks": [
      0,
      0,
      121,
      0,
      0,
      0,
      0,
      0
    ],
    "constitution": 3,
    "originGame": "FE8",
    "eyeX": 3,
    "eyeY": 4,
    "mouthX": 2,
    "mouthY": 6
  },
  {
    "name": "Rennac",
    "portraitPath": "portraits/FE8/rennac.png",
    "paletteString": "344FFF635F3B7D2AD3252C258720D60D5109EB109819511D1B13C93C3667FE7F",
    "description1": "A lazy, greedy, but exceptional",
    "description2": "fighter from the Republic of Carcino.",
    "characterClass": "ROGUE",
    "level": 1,
    "bases": {
      "hp": 12,
      "str": 7,
      "skl": 15,
      "spd": 8,
      "def": 7,
      "res": 11,
      "lck": 5
    },
    "growths": {
      "hp": 65,
      "str": 25,
      "skl": 45,
      "spd": 60,
      "def": 25,
      "res": 30,
      "lck": 25
    },
    "weaponRanks": [
      121,
      0,
      0,
      0,
      0,
      0,
      0,
      0
    ],
    "constitution": 0,
    "originGame": "FE8",
    "eyeX": 3,
    "eyeY": 3,
    "mouthX": 2,
    "mouthY": 5
  },
  {
    "name": "Duessel",
    "portraitPath": "portraits/FE8/duessel.png",
    "paletteString": "344FFF635F3B7D2AD3252C258720F34D4D350925B710710CAC14B85A5B6BFE7F",
    "description1": "A courageous general in Grado's army.",
    "description2": "He's better known as Obsidian.",
    "characterClass": "GREAT_KNIGHT",
    "level": 8,
    "bases": {
      "hp": 20,
      "str": 9,
      "skl": 8,
      "spd": 6,
      "def": 6,
      "res": 6,
      "lck": 8
    },
    "growths": {
      "hp": 85,
      "str": 55,
      "skl": 40,
      "spd": 30,
      "def": 45,
      "res": 30,
      "lck": 20
    },
    "weaponRanks": [
      181,
      181,
      181,
      0,
      0,
      0,
      0,
      0
    ],
    "constitution": 2,
    "originGame": "FE8",
    "eyeX": 3,
    "eyeY": 3,
    "mouthX": 2,
    "mouthY": 5
  },
  {
    "name": "Myrrh",
    "portraitPath": "portraits/FE8/myrrh.png",
    "paletteString": "344FDF6F3F477D2ED3252C2587202E55CB34FF23F8122D2A2E28BB0C7410FE7F",
    "description1": "A young, pure-hearted girl from",
    "description2": "Darkling Woods. She tends to be shy.",
    "characterClass": "MANAKETE_F",
    "level": 1,
    "bases": {
      "hp": 3,
      "str": 3,
      "skl": 1,
      "spd": 3,
      "def": 0,
      "res": 5,
      "lck": 3
    },
    "growths": {
      "hp": 130,
      "str": 90,
      "skl": 85,
      "spd": 65,
      "def": 150,
      "res": 30,
      "lck": 30
    },
    "weaponRanks": [
      0,
      0,
      0,
      0,
      0,
      0,
      0,
      0
    ],
    "constitution": 0,
    "originGame": "FE8",
    "eyeX": 3,
    "eyeY": 5,
    "mouthX": 2,
    "mouthY": 7
  },
  {
    "name": "Knoll",
    "portraitPath": "portraits/FE8/knoll.png",
    "paletteString": "344FFF6B7F37BD26D3252C258720B66E12564B416B45EA38C924554E1963FE7F",
    "description1": "One of Grado's royal mages. He knows",
    "description2": "the riddle of the Dark Stone.",
    "characterClass": "SHAMAN",
    "level": 9,
    "bases": {
      "hp": 5,
      "str": 10,
      "skl": 8,
      "spd": 6,
      "def": 0,
      "res": 6,
      "lck": 0
    },
    "growths": {
      "hp": 70,
      "str": 50,
      "skl": 40,
      "spd": 35,
      "def": 10,
      "res": 45,
      "lck": 20
    },
    "weaponRanks": [
      0,
      0,
      0,
      0,
      0,
      0,
      0,
      71
    ],
    "constitution": 0,
    "originGame": "FE8",
    "eyeX": 3,
    "eyeY": 3,
    "mouthX": 2,
    "mouthY": 5
  },
  {
    "name": "Joshua",
    "portraitPath": "portraits/FE8/joshua.png",
    "paletteString": "344FFF635F3B7D2AD3252C2587207C0457046E0CAA3926294D39EA2C372AFE7F",
    "description1": "A wandering swordsman from Jehanna.",
    "description2": "He loves to gamble.",
    "characterClass": "MYRMIDON",
    "level": 5,
    "bases": {
      "hp": 8,
      "str": 4,
      "skl": 4,
      "spd": 5,
      "def": 3,
      "res": 2,
      "lck": 7
    },
    "growths": {
      "hp": 80,
      "str": 35,
      "skl": 55,
      "spd": 55,
      "def": 20,
      "res": 20,
      "lck": 30
    },
    "weaponRanks": [
      71,
      0,
      0,
      0,
      0,
      0,
      0,
      0
    ],
    "constitution": 0,
    "originGame": "FE8",
    "eyeX": 3,
    "eyeY": 3,
    "mouthX": 2,
    "mouthY": 5
  },
  {
    "name": "Syrene",
    "portraitPath": "portraits/FE8/syrene.png",
    "paletteString": "344FFF635F3B7D2AD3252C258720271F651A881D345BEC390619581E1963FE7F",
    "description1": "The dutiful commander of the 3rd",
    "description2": "battalion of Frelia's pegasus knights.",
    "characterClass": "FALCON_KNIGHT",
    "level": 1,
    "bases": {
      "hp": 7,
      "str": 6,
      "skl": 6,
      "spd": 8,
      "def": 5,
      "res": 8,
      "lck": 12
    },
    "growths": {
      "hp": 70,
      "str": 40,
      "skl": 50,
      "spd": 60,
      "def": 20,
      "res": 50,
      "lck": 30
    },
    "weaponRanks": [
      71,
      181,
      0,
      0,
      0,
      0,
      0,
      0
    ],
    "constitution": 1,
    "originGame": "FE8",
    "eyeX": 3,
    "eyeY": 3,
    "mouthX": 2,
    "mouthY": 5
  },
  {
    "name": "Tana",
    "portraitPath": "portraits/FE8/tana.png",
    "paletteString": "344FDF6F3F477D2ED3252C258720AB5D654104253F193B08FF272B465373FE7F",
    "description1": "A young lady of Frelia. She is both",
    "description2": "cheery and sociable.",
    "characterClass": "PEGASUS_KNIGHT",
    "level": 4,
    "bases": {
      "hp": 6,
      "str": 3,
      "skl": 4,
      "spd": 8,
      "def": 3,
      "res": 5,
      "lck": 8
    },
    "growths": {
      "hp": 65,
      "str": 45,
      "skl": 40,
      "spd": 65,
      "def": 20,
      "res": 25,
      "lck": 60
    },
    "weaponRanks": [
      0,
      31,
      0,
      0,
      0,
      0,
      0,
      0
    ],
    "constitution": 0,
    "originGame": "FE8",
    "eyeX": 3,
    "eyeY": 4,
    "mouthX": 2,
    "mouthY": 6
  }
]